README.txt
setup.py
csapi/__init__.py
csapi/cli.py
csapi/csapi.py
csapi.egg-info/PKG-INFO
csapi.egg-info/SOURCES.txt
csapi.egg-info/dependency_links.txt
csapi.egg-info/pbr.json
csapi.egg-info/requires.txt
csapi.egg-info/top_level.txt