Metadata-Version: 1.0
Name: csapi
Version: 0.0.8
Summary: A minimalist wrapper around the Apache CloudStack API.
Home-page: https://github.com/swill/csapi
Author: Will Stevens
Author-email: wstevens@cloudops.com
License: Apache Licence v2.0
Platform: UNKNOWN
